saveMZ/__init__.py
saveMZ-1.0.0.dist-info/LICENSE
saveMZ-1.0.0.dist-info/METADATA
saveMZ-1.0.0.dist-info/WHEEL
saveMZ-1.0.0.dist-info/top_level.txt
saveMZ-1.0.0.dist-info/RECORD
