Metadata-Version: 2.1
Name: saveMZ
Version: 1.0.0
Summary: It's easy save in Python with Json file
Author-email: Mozan <jansses70@gmail.com>
Project-URL: Homepage, https://github.com/imozan/saveMZ.git
Project-URL: Bug Tracker, https://github.com/imozan/saveMZ/issues
Classifier: Programming Language :: Python :: 3
Classifier: Operating System :: OS Independent 
Classifier: License :: OSI Approved :: MIT License 
Requires-Python: >=3.7
License-File: LICENSE
